sdgs/__init__.py
sdgs/auth/__init__.py
sdgs/auth/base.py
sdgs/auth/token.py
sdgs/base.py
sdgs/model/__init__.py
sdgs/model/capaian_nasional.py
sdgs/model/wilayah.py
sdgs/response.py
sdgs/sdgs.py
sdgs/survey_individu/__init__.py
sdgs/survey_individu/base.py
sdgs/survey_individu/survey_paged_data.py
sdgs/survey_individu/tambah/__init__.py
sdgs/survey_individu/tambah/agama.py
sdgs/survey_individu/tambah/disabilitas.py
sdgs/survey_individu/tambah/fasilitas_kesehatan.py
sdgs/survey_individu/tambah/individu.py
sdgs/survey_individu/tambah/kondisi_pekerjaan.py
sdgs/survey_individu/tambah/pekerjaan_utama.py
sdgs/survey_individu/tambah/pendidikan_diikuti.py
sdgs/survey_individu/tambah/pendidikan_tertinggi.py
sdgs/survey_individu/tambah/penghasilan.py
sdgs/survey_individu/tambah/penyakit_diderita.py
sdgs/survey_individu/tambah/status_pernikahan.py
sdgs/utils.py
sdgs/version.py
sdgs_dashboard-0.2.0.dist-info/LICENSE
sdgs_dashboard-0.2.0.dist-info/WHEEL
sdgs_dashboard-0.2.0.dist-info/METADATA
sdgs_dashboard-0.2.0.dist-info/RECORD
