Metadata-Version: 2.1
Name: sdgs-dashboard
Version: 0.2.0
Summary:  Modul python untuk dashboard sdgs kemendesa.
Home-page: https://github.com/hexatester/sdgs-dashboard
License: MIT
Keywords: sdgs,sdgs-dashboard,kemendesa
Author: hexatester
Author-email: hexatester@protonmail.com
Requires-Python: >=3.7.10,<4.0.0
Classifier: Development Status :: 4 - Beta
Classifier: Intended Audience :: Developers
Classifier: License :: OSI Approved :: MIT License
Classifier: Programming Language :: Python
Classifier: Programming Language :: Python :: 3
Classifier: Programming Language :: Python :: 3.7
Classifier: Programming Language :: Python :: 3.8
Classifier: Programming Language :: Python :: 3.9
Requires-Dist: attrs (>=21.2.0,<22.0.0)
Requires-Dist: beautifulsoup4 (>=4.9.3,<5.0.0)
Requires-Dist: cattrs (>=1.8.0,<2.0.0)
Requires-Dist: python-dateutil (>=2.8.2,<3.0.0)
Requires-Dist: requests (>=2.26.0,<3.0.0)
Requires-Dist: ujson (>=4.0.2,<5.0.0)
Project-URL: Repository, https://github.com/hexatester/sdgs-dashboard
